{
	"Audio" : 
	{
		"music" : true,
		"musiclevel" : 83,
		"Sound" : true,
		"Soundlevel" : 85
	},
	"Bought_Skins" : 
	[
		true,
		true,
		true,
		true,
		true,
		false,
		true,
		false,
		true
	],
	"coins" : 26,
	"Player" : 
	{
		"File" : "Assets/character_2.png",
		"ID" : "character_2"
	},
	"quotes" :
	[
		"Franky is our favorite Asian!",
		"Is this EZ mode?",
		"How about you actually get good?",
		"Peukie doen?",
		"Double Destructor!",
		"Sheeeeesh!!!",
		"Coen ga je nog wat doen?",
		"Nick heeft weer nicks gedaan",
		"Daniiil",
		"Ik zie alles breedbeeld",
		"Lag!",
		"@everyone",
		"Push Push Push!",
		"Pull Harder!",
		"Apex?",
		"Teams?",
		"Wat een kut game!",
		"Franky ligt waarschijnlijk nog in bed",
		"En wat zijn jullie aan het doen?",
		"Ik ga even ochtend eten"
	],
	"Score" :
	{
		"highscore" : 186
	},
	"Theme" : 
	{
		"File" : "Assets/cyan_blue.png",
		"ID" : "cyan_blue_theme",
		"obstacleColor" : "Blue",
		"wallColor" : "Cyan"
	}
}